secmod/__init__.py
secmod-0.1.0.dist-info/LICENSE.md
secmod-0.1.0.dist-info/METADATA
secmod-0.1.0.dist-info/WHEEL
secmod-0.1.0.dist-info/top_level.txt
secmod-0.1.0.dist-info/RECORD
