Metadata-Version: 2.1
Name: secmod
Version: 0.1.0
Summary: secure module interface
Home-page: https://github.com/cloasdata/secmod
Author: Simon Bauer
Author-email: code@seimenadventure.de
License: MIT
Keywords: python,module,import,importlib
Platform: UNKNOWN
Classifier: Programming Language :: Python :: 3
Classifier: License :: OSI Approved :: MIT License
Classifier: Operating System :: OS Independent
License-File: LICENSE.md
Requires-Dist: importlib ; python_version >= "3.10"
Provides-Extra: test
Requires-Dist: pytest (>=7.0.0) ; extra == 'test'
